{"nm":"Not found gif","ddd":0,"h":137,"w":132.15,"meta":{"g":"LottieFiles Figma v112"},"layers":[{"ty":4,"nm":"larm","sr":1,"st":0,"op":166,"ip":0,"hd":false,"ddd":0,"bm":0,"hasMask":false,"ao":0,"ks":{"a":{"a":0,"k":[4.91,21.83]},"s":{"a":0,"k":[100,-100]},"sk":{"a":0,"k":0},"p":{"a":1,"k":[{"o":{"x":0.65,"y":0},"i":{"x":0.35,"y":0},"s":[14.22,95.89],"t":0},{"o":{"x":0.65,"y":0},"i":{"x":0.35,"y":0},"s":[14.22,95.89],"t":27},{"o":{"x":0.65,"y":0},"i":{"x":0.35,"y":0},"s":[10.02,101.52],"t":45},{"o":{"x":0.65,"y":0},"i":{"x":0.35,"y":0},"s":[10.02,101.52],"t":69},{"o":{"x":0.65,"y":0},"i":{"x":0.35,"y":0},"s":[14.22,99.89],"t":87},{"o":{"x":0.65,"y":0},"i":{"x":0.35,"y":0},"s":[14.22,99.89],"t":147},{"o":{"x":0.65,"y":0},"i":{"x":0.35,"y":0},"s":[14.22,95.89],"t":165},{"s":[14.22,95.89],"t":192}]},"r":{"a":1,"k":[{"o":{"x":0.65,"y":0},"i":{"x":0.35,"y":0},"s":[-153.7],"t":0},{"o":{"x":0.65,"y":0},"i":{"x":0.35,"y":0},"s":[-153.7],"t":27},{"o":{"x":0.65,"y":0},"i":{"x":0.35,"y":0},"s":[-166.51],"t":45},{"o":{"x":0.65,"y":0},"i":{"x":0.35,"y":0},"s":[-166.51],"t":69},{"o":{"x":0.65,"y":0},"i":{"x":0.35,"y":0},"s":[-153.7],"t":87},{"o":{"x":0.65,"y":0},"i":{"x":0.35,"y":0},"s":[-153.7],"t":147},{"o":{"x":0.65,"y":0},"i":{"x":0.35,"y":0},"s":[-153.7],"t":165},{"s":[-153.7],"t":192}]},"sa":{"a":0,"k":0},"o":{"a":0,"k":100}},"shapes":[{"ty":"sh","bm":0,"hd":false,"nm":"","d":1,"ks":{"a":0,"k":{"c":true,"i":[[0,0],[3.528892766572884,0],[0,11.967182897376226],[-3.528892766572884,0],[0,-11.967182897376226]],"o":[[0,11.967182897376226],[-3.528892766572884,0],[0,-11.967182897376226],[3.528892766572884,0],[0,0]],"v":[[9.529949421816333,21.679967024873278],[3.131407592316048,43.35000277763255],[0.019389520695455405,22.345362256511624],[3.131407592316048,0],[9.529949421816333,21.679967024873278]]}}},{"ty":"st","bm":0,"hd":false,"nm":"","lc":1,"lj":1,"ml":4,"o":{"a":0,"k":100},"w":{"a":1,"k":[{"o":{"x":0.65,"y":0},"i":{"x":0.35,"y":0},"s":[1],"t":0},{"o":{"x":0.65,"y":0},"i":{"x":0.35,"y":0},"s":[1],"t":27},{"o":{"x":0.65,"y":0},"i":{"x":0.35,"y":0},"s":[1],"t":45},{"o":{"x":0.65,"y":0},"i":{"x":0.35,"y":0},"s":[1],"t":69},{"o":{"x":0.65,"y":0},"i":{"x":0.35,"y":0},"s":[1],"t":87},{"o":{"x":0.65,"y":0},"i":{"x":0.35,"y":0},"s":[1],"t":147},{"o":{"x":0.65,"y":0},"i":{"x":0.35,"y":0},"s":[1],"t":165},{"s":[1],"t":192}]},"c":{"a":0,"k":[0.251,0.3059,0.302]}},{"ty":"fl","bm":0,"hd":false,"nm":"","c":{"a":0,"k":[1,1,1]},"r":1,"o":{"a":0,"k":100}}],"ind":1},{"ty":4,"nm":"rarm","sr":1,"st":0,"op":166,"ip":0,"hd":false,"ddd":0,"bm":0,"hasMask":false,"ao":0,"ks":{"a":{"a":0,"k":[4.91,21.83]},"s":{"a":0,"k":[100,100]},"sk":{"a":0,"k":0},"p":{"a":1,"k":[{"o":{"x":0.65,"y":0},"i":{"x":0.35,"y":0},"s":[118.22,92.89],"t":0},{"o":{"x":0.65,"y":0},"i":{"x":0.35,"y":0},"s":[118.22,92.89],"t":27},{"o":{"x":0.65,"y":0},"i":{"x":0.35,"y":0},"s":[108.01,101.52],"t":45},{"o":{"x":0.65,"y":0},"i":{"x":0.35,"y":0},"s":[108.01,101.52],"t":69},{"o":{"x":0.65,"y":0},"i":{"x":0.35,"y":0},"s":[119.24,99.89],"t":87},{"o":{"x":0.65,"y":0},"i":{"x":0.35,"y":0},"s":[119.24,99.89],"t":147},{"o":{"x":0.65,"y":0},"i":{"x":0.35,"y":0},"s":[118.22,92.89],"t":165},{"s":[118.22,92.89],"t":192}]},"r":{"a":1,"k":[{"o":{"x":0.65,"y":0},"i":{"x":0.35,"y":0},"s":[-26.3],"t":0},{"o":{"x":0.65,"y":0},"i":{"x":0.35,"y":0},"s":[-26.3],"t":27},{"o":{"x":0.65,"y":0},"i":{"x":0.35,"y":0},"s":[-13.47],"t":45},{"o":{"x":0.65,"y":0},"i":{"x":0.35,"y":0},"s":[-13.47],"t":69},{"o":{"x":0.65,"y":0},"i":{"x":0.35,"y":0},"s":[-26.3],"t":87},{"o":{"x":0.65,"y":0},"i":{"x":0.35,"y":0},"s":[-26.3],"t":147},{"o":{"x":0.65,"y":0},"i":{"x":0.35,"y":0},"s":[-26.3],"t":165},{"s":[-26.3],"t":192}]},"sa":{"a":0,"k":0},"o":{"a":0,"k":100}},"shapes":[{"ty":"sh","bm":0,"hd":false,"nm":"","d":1,"ks":{"a":0,"k":{"c":true,"i":[[0,0],[3.528892766572884,0],[0,11.967182897376226],[-3.528892766572884,0],[0,-11.967182897376226]],"o":[[0,11.967182897376226],[-3.528892766572884,0],[0,-11.967182897376226],[3.528892766572884,0],[0,0]],"v":[[9.529949421816333,21.679967024873278],[3.131407592316048,43.35000277763255],[0.019389520695455405,22.345362256511624],[3.131407592316048,0],[9.529949421816333,21.679967024873278]]}}},{"ty":"st","bm":0,"hd":false,"nm":"","lc":1,"lj":1,"ml":4,"o":{"a":0,"k":100},"w":{"a":1,"k":[{"o":{"x":0.65,"y":0},"i":{"x":0.35,"y":0},"s":[1],"t":0},{"o":{"x":0.65,"y":0},"i":{"x":0.35,"y":0},"s":[1],"t":27},{"o":{"x":0.65,"y":0},"i":{"x":0.35,"y":0},"s":[1],"t":45},{"o":{"x":0.65,"y":0},"i":{"x":0.35,"y":0},"s":[1],"t":69},{"o":{"x":0.65,"y":0},"i":{"x":0.35,"y":0},"s":[1],"t":87},{"o":{"x":0.65,"y":0},"i":{"x":0.35,"y":0},"s":[1],"t":147},{"o":{"x":0.65,"y":0},"i":{"x":0.35,"y":0},"s":[1],"t":165},{"s":[1],"t":192}]},"c":{"a":0,"k":[0.251,0.3059,0.302]}},{"ty":"fl","bm":0,"hd":false,"nm":"","c":{"a":0,"k":[1,1,1]},"r":1,"o":{"a":0,"k":100}}],"ind":2},{"ty":4,"nm":"shadow_reference","sr":1,"st":0,"op":166,"ip":0,"hd":false,"ddd":0,"bm":0,"hasMask":false,"ao":0,"ks":{"a":{"a":0,"k":[30.98,9.76]},"s":{"a":0,"k":[100,100]},"sk":{"a":0,"k":0},"p":{"a":1,"k":[{"o":{"x":0.65,"y":0},"i":{"x":0.35,"y":0},"s":[62.92,73.76],"t":0},{"o":{"x":0.65,"y":0},"i":{"x":0.35,"y":0},"s":[62.92,73.76],"t":27},{"o":{"x":0.65,"y":0},"i":{"x":0.35,"y":0},"s":[58.92,73.76],"t":45},{"o":{"x":0.65,"y":0},"i":{"x":0.35,"y":0},"s":[58.92,73.76],"t":69},{"o":{"x":0.65,"y":0},"i":{"x":0.35,"y":0},"s":[66.92,73.76],"t":87},{"o":{"x":0.65,"y":0},"i":{"x":0.35,"y":0},"s":[66.92,73.76],"t":147},{"o":{"x":0.65,"y":0},"i":{"x":0.35,"y":0},"s":[62.92,73.76],"t":165},{"s":[62.92,73.76],"t":192}]},"r":{"a":0,"k":0},"sa":{"a":0,"k":0},"o":{"a":0,"k":100}},"shapes":[{"ty":"sh","bm":0,"hd":false,"nm":"","d":1,"ks":{"a":0,"k":{"c":true,"i":[[0,0],[17.11,0],[0,5.39],[-17.11,0],[0,-5.39]],"o":[[0,5.39],[-17.11,0],[0,-5.39],[17.11,0],[0,0]],"v":[[61.97,9.76],[30.98,19.52],[0,9.76],[30.98,0],[61.97,9.76]]}}},{"ty":"fl","bm":0,"hd":false,"nm":"","c":{"a":0,"k":[0.8655,0.8913,0.9327]},"r":1,"o":{"a":0,"k":100}}],"ind":3},{"ty":4,"nm":"body","sr":1,"st":0,"op":166,"ip":0,"hd":false,"ddd":0,"bm":0,"hasMask":false,"ao":0,"ks":{"a":{"a":0,"k":[36.92,36.5]},"s":{"a":0,"k":[100,100]},"sk":{"a":0,"k":0},"p":{"a":1,"k":[{"o":{"x":0.65,"y":0},"i":{"x":0.35,"y":0},"s":[63.07,100.65],"t":0},{"o":{"x":0.65,"y":0},"i":{"x":0.35,"y":0},"s":[63.07,100.65],"t":27},{"o":{"x":0.65,"y":0},"i":{"x":0.35,"y":0},"s":[59.07,100.65],"t":45},{"o":{"x":0.65,"y":0},"i":{"x":0.35,"y":0},"s":[59.07,100.65],"t":69},{"o":{"x":0.65,"y":0},"i":{"x":0.35,"y":0},"s":[67.07,100.65],"t":87},{"o":{"x":0.65,"y":0},"i":{"x":0.35,"y":0},"s":[67.07,100.65],"t":147},{"o":{"x":0.65,"y":0},"i":{"x":0.35,"y":0},"s":[63.07,100.65],"t":165},{"s":[63.07,100.65],"t":192}]},"r":{"a":0,"k":0},"sa":{"a":0,"k":0},"o":{"a":0,"k":100}},"shapes":[{"ty":"sh","bm":0,"hd":false,"nm":"","d":1,"ks":{"a":0,"k":{"c":true,"i":[[0,0],[-3.9638317921135138,-4.431712328040437],[0,-7.449260272751116],[20.307168402310186,0],[0,23.29387670850917],[-2.957934779541994,3.027506848818635],[-15.287642715814682,0]],"o":[[15.287642715814682,0],[2.957934779541994,3.017547944710679],[0,23.29387670850917],[-20.307168402310186,0],[0,-7.449260272751116],[3.9638317921135138,-4.431712328040437],[0,0]],"v":[[36.770017528851994,0],[68.90892504933015,7.688273971342061],[73.54999443406606,22.91543835240684],[36.770017528851994,72.69999998807907],[0,22.91543835240684],[4.641069384735923,7.688273971342061],[36.770017528851994,0]]}}},{"ty":"st","bm":0,"hd":false,"nm":"","lc":1,"lj":1,"ml":4,"o":{"a":0,"k":100},"w":{"a":1,"k":[{"o":{"x":0.65,"y":0},"i":{"x":0.35,"y":0},"s":[1],"t":0},{"o":{"x":0.65,"y":0},"i":{"x":0.35,"y":0},"s":[1],"t":27},{"o":{"x":0.65,"y":0},"i":{"x":0.35,"y":0},"s":[1],"t":45},{"o":{"x":0.65,"y":0},"i":{"x":0.35,"y":0},"s":[1],"t":69},{"o":{"x":0.65,"y":0},"i":{"x":0.35,"y":0},"s":[1],"t":87},{"o":{"x":0.65,"y":0},"i":{"x":0.35,"y":0},"s":[1],"t":147},{"o":{"x":0.65,"y":0},"i":{"x":0.35,"y":0},"s":[1],"t":165},{"s":[1],"t":192}]},"c":{"a":0,"k":[0.251,0.3059,0.302]}},{"ty":"fl","bm":0,"hd":false,"nm":"","c":{"a":0,"k":[1,1,1]},"r":1,"o":{"a":0,"k":100}}],"ind":4},{"ty":4,"nm":"reye","sr":1,"st":0,"op":166,"ip":0,"hd":false,"ddd":0,"bm":0,"hasMask":false,"ao":0,"ks":{"a":{"a":0,"k":[7.5,3]},"s":{"a":0,"k":[100,100]},"sk":{"a":0,"k":0},"p":{"a":1,"k":[{"o":{"x":0.65,"y":0},"i":{"x":0.35,"y":0},"s":[67,35.5],"t":0},{"o":{"x":0.65,"y":0},"i":{"x":0.35,"y":0},"s":[67,35.5],"t":27},{"o":{"x":0.65,"y":0},"i":{"x":0.35,"y":0},"s":[90,35.5],"t":45},{"o":{"x":0.65,"y":0},"i":{"x":0.35,"y":0},"s":[90,35.5],"t":69},{"o":{"x":0.65,"y":0},"i":{"x":0.35,"y":0},"s":[90,35.5],"t":87},{"o":{"x":0.65,"y":0},"i":{"x":0.35,"y":0},"s":[90,35.5],"t":147},{"o":{"x":0.65,"y":0},"i":{"x":0.35,"y":0},"s":[67,35.5],"t":165},{"s":[67,35.5],"t":192}]},"r":{"a":0,"k":-90},"sa":{"a":0,"k":0},"o":{"a":0,"k":100}},"shapes":[{"ty":"sh","bm":0,"hd":false,"nm":"","d":1,"ks":{"a":0,"k":{"c":true,"i":[[0,-1.66],[0,0],[1.66,0],[0,0],[0,1.66],[0,0],[-1.66,0],[0,0]],"o":[[0,0],[0,1.66],[0,0],[-1.66,0],[0,0],[0,-1.66],[0,0],[1.66,0]],"v":[[15,3],[15,3],[12,6],[3,6],[0,3],[0,3],[3,0],[12,0]]}}},{"ty":"fl","bm":0,"hd":false,"nm":"","c":{"a":1,"k":[{"o":{"x":0.65,"y":0},"i":{"x":0.35,"y":0},"s":[0.0981,0.9961,0.6667],"t":0},{"o":{"x":0.65,"y":0},"i":{"x":0.35,"y":0},"s":[0.0981,0.9961,0.6667],"t":27},{"o":{"x":0.65,"y":0},"i":{"x":0.35,"y":0},"s":[0.0981,0.9961,0.6667],"t":45},{"o":{"x":0.65,"y":0},"i":{"x":0.35,"y":0},"s":[0.0981,0.9961,0.6667],"t":69},{"o":{"x":0.65,"y":0},"i":{"x":0.35,"y":0},"s":[0.0289,1,0.6601],"t":87},{"o":{"x":0.65,"y":0},"i":{"x":0.35,"y":0},"s":[0.0289,1,0.6601],"t":147},{"o":{"x":0.65,"y":0},"i":{"x":0.35,"y":0},"s":[0.0981,0.9961,0.6667],"t":165},{"s":[0.0981,0.9961,0.6667],"t":192}]},"r":1,"o":{"a":0,"k":100}}],"ind":5},{"ty":4,"nm":"leye","sr":1,"st":0,"op":166,"ip":0,"hd":false,"ddd":0,"bm":0,"hasMask":false,"ao":0,"ks":{"a":{"a":0,"k":[7.5,3]},"s":{"a":0,"k":[100,100]},"sk":{"a":0,"k":0},"p":{"a":1,"k":[{"o":{"x":0.65,"y":0},"i":{"x":0.35,"y":0},"s":[31,35.5],"t":0},{"o":{"x":0.65,"y":0},"i":{"x":0.35,"y":0},"s":[31,35.5],"t":27},{"o":{"x":0.65,"y":0},"i":{"x":0.35,"y":0},"s":[54,35.5],"t":45},{"o":{"x":0.65,"y":0},"i":{"x":0.35,"y":0},"s":[54,35.5],"t":69},{"o":{"x":0.65,"y":0},"i":{"x":0.35,"y":0},"s":[44,35.5],"t":87},{"o":{"x":0.65,"y":0},"i":{"x":0.35,"y":0},"s":[44,35.5],"t":147},{"o":{"x":0.65,"y":0},"i":{"x":0.35,"y":0},"s":[31,35.5],"t":165},{"s":[31,35.5],"t":192}]},"r":{"a":0,"k":-90},"sa":{"a":0,"k":0},"o":{"a":0,"k":100}},"shapes":[{"ty":"sh","bm":0,"hd":false,"nm":"","d":1,"ks":{"a":0,"k":{"c":true,"i":[[0,-1.66],[0,0],[1.66,0],[0,0],[0,1.66],[0,0],[-1.66,0],[0,0]],"o":[[0,0],[0,1.66],[0,0],[-1.66,0],[0,0],[0,-1.66],[0,0],[1.66,0]],"v":[[15,3],[15,3],[12,6],[3,6],[0,3],[0,3],[3,0],[12,0]]}}},{"ty":"fl","bm":0,"hd":false,"nm":"","c":{"a":1,"k":[{"o":{"x":0.65,"y":0},"i":{"x":0.35,"y":0},"s":[0.0981,0.9961,0.6667],"t":0},{"o":{"x":0.65,"y":0},"i":{"x":0.35,"y":0},"s":[0.0981,0.9961,0.6667],"t":27},{"o":{"x":0.65,"y":0},"i":{"x":0.35,"y":0},"s":[0.0981,0.9961,0.6667],"t":45},{"o":{"x":0.65,"y":0},"i":{"x":0.35,"y":0},"s":[0.0981,0.9961,0.6667],"t":69},{"o":{"x":0.65,"y":0},"i":{"x":0.35,"y":0},"s":[0.0289,1,0.6601],"t":87},{"o":{"x":0.65,"y":0},"i":{"x":0.35,"y":0},"s":[0.0289,1,0.6601],"t":147},{"o":{"x":0.65,"y":0},"i":{"x":0.35,"y":0},"s":[0.0981,0.9961,0.6667],"t":165},{"s":[0.0981,0.9961,0.6667],"t":192}]},"r":1,"o":{"a":0,"k":100}}],"ind":6},{"ty":4,"nm":"visor","sr":1,"st":0,"op":166,"ip":0,"hd":false,"ddd":0,"bm":0,"hasMask":false,"ao":0,"ks":{"a":{"a":1,"k":[{"o":{"x":0.65,"y":0},"i":{"x":0.35,"y":0},"s":[35,16],"t":0},{"o":{"x":0.65,"y":0},"i":{"x":0.35,"y":0},"s":[35,16],"t":27},{"o":{"x":0.65,"y":0},"i":{"x":0.35,"y":0},"s":[35,16],"t":45},{"o":{"x":0.65,"y":0},"i":{"x":0.35,"y":0},"s":[35,16],"t":69},{"o":{"x":0.65,"y":0},"i":{"x":0.35,"y":0},"s":[39.5,16],"t":87},{"o":{"x":0.65,"y":0},"i":{"x":0.35,"y":0},"s":[39.5,16],"t":147},{"o":{"x":0.65,"y":0},"i":{"x":0.35,"y":0},"s":[35,16],"t":165},{"s":[35,16],"t":192}]},"s":{"a":0,"k":[100,100]},"sk":{"a":0,"k":0},"p":{"a":1,"k":[{"o":{"x":0.65,"y":0},"i":{"x":0.35,"y":0},"s":[53,34],"t":0},{"o":{"x":0.65,"y":0},"i":{"x":0.35,"y":0},"s":[53,34],"t":27},{"o":{"x":0.65,"y":0},"i":{"x":0.35,"y":0},"s":[68,34],"t":45},{"o":{"x":0.65,"y":0},"i":{"x":0.35,"y":0},"s":[68,34],"t":69},{"o":{"x":0.65,"y":0},"i":{"x":0.35,"y":0},"s":[67.5,36],"t":87},{"o":{"x":0.65,"y":0},"i":{"x":0.35,"y":0},"s":[67.5,36],"t":147},{"o":{"x":0.65,"y":0},"i":{"x":0.35,"y":0},"s":[53,34],"t":165},{"s":[53,34],"t":192}]},"r":{"a":0,"k":0},"sa":{"a":0,"k":0},"o":{"a":0,"k":100}},"shapes":[{"ty":"sh","bm":0,"hd":false,"nm":"","d":1,"ks":{"a":1,"k":[{"o":{"x":0.65,"y":0},"i":{"x":0.35,"y":0},"s":[{"c":true,"i":[[0,-8.83],[0,0],[8.83,0],[0,0],[0,8.83],[0,0],[-8.83,0],[0,0]],"o":[[0,0],[0,8.83],[0,0],[-8.83,0],[0,0],[0,-8.83],[0,0],[8.83,0]],"v":[[70,16],[70,16],[54,32],[16,32],[0,16],[0,16],[16,0],[54,0]]}],"t":0},{"o":{"x":0.65,"y":0},"i":{"x":0.35,"y":0},"s":[{"c":true,"i":[[0,-8.83],[0,0],[8.83,0],[0,0],[0,8.83],[0,0],[-8.83,0],[0,0]],"o":[[0,0],[0,8.83],[0,0],[-8.83,0],[0,0],[0,-8.83],[0,0],[8.83,0]],"v":[[70,16],[70,16],[54,32],[16,32],[0,16],[0,16],[16,0],[54,0]]}],"t":27},{"o":{"x":0.65,"y":0},"i":{"x":0.35,"y":0},"s":[{"c":true,"i":[[0,-8.83],[0,0],[8.83,0],[0,0],[0,8.83],[0,0],[-8.83,0],[0,0]],"o":[[0,0],[0,8.83],[0,0],[-8.83,0],[0,0],[0,-8.83],[0,0],[8.83,0]],"v":[[70,16],[70,16],[54,32],[16,32],[0,16],[0,16],[16,0],[54,0]]}],"t":45},{"o":{"x":0.65,"y":0},"i":{"x":0.35,"y":0},"s":[{"c":true,"i":[[0,-8.83],[0,0],[8.83,0],[0,0],[0,8.83],[0,0],[-8.83,0],[0,0]],"o":[[0,0],[0,8.83],[0,0],[-8.83,0],[0,0],[0,-8.83],[0,0],[8.83,0]],"v":[[70,16],[70,16],[54,32],[16,32],[0,16],[0,16],[16,0],[54,0]]}],"t":69},{"o":{"x":0.65,"y":0},"i":{"x":0.35,"y":0},"s":[{"c":true,"i":[[0,-8.83],[0,0],[8.83,0],[0,0],[0,8.83],[0,0],[-8.83,0],[0,0]],"o":[[0,0],[0,8.83],[0,0],[-8.83,0],[0,0],[0,-8.83],[0,0],[8.83,0]],"v":[[79,16],[79,16],[63,32],[16,32],[0,16],[0,16],[16,0],[63,0]]}],"t":87},{"o":{"x":0.65,"y":0},"i":{"x":0.35,"y":0},"s":[{"c":true,"i":[[0,-8.83],[0,0],[8.83,0],[0,0],[0,8.83],[0,0],[-8.83,0],[0,0]],"o":[[0,0],[0,8.83],[0,0],[-8.83,0],[0,0],[0,-8.83],[0,0],[8.83,0]],"v":[[79,16],[79,16],[63,32],[16,32],[0,16],[0,16],[16,0],[63,0]]}],"t":147},{"o":{"x":0.65,"y":0},"i":{"x":0.35,"y":0},"s":[{"c":true,"i":[[0,-8.83],[0,0],[8.83,0],[0,0],[0,8.83],[0,0],[-8.83,0],[0,0]],"o":[[0,0],[0,8.83],[0,0],[-8.83,0],[0,0],[0,-8.83],[0,0],[8.83,0]],"v":[[70,16],[70,16],[54,32],[16,32],[0,16],[0,16],[16,0],[54,0]]}],"t":165},{"s":[{"c":true,"i":[[0,-8.83],[0,0],[8.83,0],[0,0],[0,8.83],[0,0],[-8.83,0],[0,0]],"o":[[0,0],[0,8.83],[0,0],[-8.83,0],[0,0],[0,-8.83],[0,0],[8.83,0]],"v":[[70,16],[70,16],[54,32],[16,32],[0,16],[0,16],[16,0],[54,0]]}],"t":192}]}},{"ty":"fl","bm":0,"hd":false,"nm":"","c":{"a":1,"k":[{"o":{"x":0.65,"y":0},"i":{"x":0.35,"y":0},"s":[0.0196,0.0942,0.1687],"t":0},{"o":{"x":0.65,"y":0},"i":{"x":0.35,"y":0},"s":[0.0196,0.0942,0.1687],"t":27},{"o":{"x":0.65,"y":0},"i":{"x":0.35,"y":0},"s":[0.0196,0.0942,0.1687],"t":45},{"o":{"x":0.65,"y":0},"i":{"x":0.35,"y":0},"s":[0.0196,0.0942,0.1687],"t":69},{"o":{"x":0.65,"y":0},"i":{"x":0.35,"y":0},"s":[0.0471,0.1059,0.2],"t":87},{"o":{"x":0.65,"y":0},"i":{"x":0.35,"y":0},"s":[0.0471,0.1059,0.2],"t":147},{"o":{"x":0.65,"y":0},"i":{"x":0.35,"y":0},"s":[0.0196,0.0942,0.1687],"t":165},{"s":[0.0196,0.0942,0.1687],"t":192}]},"r":1,"o":{"a":0,"k":100}}],"ind":7},{"ty":4,"nm":"head","sr":1,"st":0,"op":166,"ip":0,"hd":false,"ddd":0,"bm":0,"hasMask":false,"ao":0,"ks":{"a":{"a":1,"k":[{"o":{"x":0.65,"y":0},"i":{"x":0.35,"y":0},"s":[58.5,30.5],"t":0},{"o":{"x":0.65,"y":0},"i":{"x":0.35,"y":0},"s":[58.5,30.5],"t":27},{"o":{"x":0.65,"y":0},"i":{"x":0.35,"y":0},"s":[58.5,30.5],"t":45},{"o":{"x":0.65,"y":0},"i":{"x":0.35,"y":0},"s":[58.5,30.5],"t":69},{"o":{"x":0.65,"y":0},"i":{"x":0.35,"y":0},"s":[59.5,30.5],"t":87},{"o":{"x":0.65,"y":0},"i":{"x":0.35,"y":0},"s":[59.5,30.5],"t":147},{"o":{"x":0.65,"y":0},"i":{"x":0.35,"y":0},"s":[58.5,30.5],"t":165},{"s":[58.5,30.5],"t":192}]},"s":{"a":0,"k":[100,100]},"sk":{"a":0,"k":0},"p":{"a":1,"k":[{"o":{"x":0.65,"y":0},"i":{"x":0.35,"y":0},"s":[58.65,30.65],"t":0},{"o":{"x":0.65,"y":0},"i":{"x":0.35,"y":0},"s":[58.65,30.65],"t":27},{"o":{"x":0.65,"y":0},"i":{"x":0.35,"y":0},"s":[62.65,30.65],"t":45},{"o":{"x":0.65,"y":0},"i":{"x":0.35,"y":0},"s":[62.65,30.65],"t":69},{"o":{"x":0.65,"y":0},"i":{"x":0.35,"y":0},"s":[67.65,30.65],"t":87},{"o":{"x":0.65,"y":0},"i":{"x":0.35,"y":0},"s":[67.65,30.65],"t":147},{"o":{"x":0.65,"y":0},"i":{"x":0.35,"y":0},"s":[58.65,30.65],"t":165},{"s":[58.65,30.65],"t":192}]},"r":{"a":0,"k":0},"sa":{"a":0,"k":0},"o":{"a":0,"k":100}},"shapes":[{"ty":"sh","bm":0,"hd":false,"nm":"","d":1,"ks":{"a":1,"k":[{"o":{"x":0.65,"y":0},"i":{"x":0.35,"y":0},"s":[{"c":true,"i":[[0,0],[-8.308641024792296,-12.946016390900143],[0,-6.129704916828969],[4.36876923032296,-1.7811967209616646],[25.18525640768373,0],[6.423487178831019,12.269360653328114],[0,4.45796721223925],[-4.049589743176077,1.910557376673964],[-23.419794869402537,0]],"o":[[21.75407692085474,0],[5.954692307084034,0.6866065572422059],[0,4.995311474428802],[-5.615564101990471,13.443557374408988],[-24.327461535976486,0],[-3.6306666662957934,-2.049868852056441],[0,-4.766442622014734],[7.181538460804866,-14.558049177468801],[0,0]],"v":[[57.35256409670553,0],[106.12717947633858,21.971409831750588],[116.69999998807907,33.832786878601446],[109.24915383499402,44.888147532167984],[57.35256409670553,60.69999998807907],[6.074384614764115,46.21160654830151],[0,35.822950812636826],[6.852384614684643,25.026311470494896],[57.35256409670553,0]]}],"t":0},{"o":{"x":0.65,"y":0},"i":{"x":0.35,"y":0},"s":[{"c":true,"i":[[0,0],[-8.308641024792296,-12.946016390900143],[0,-6.129704916828969],[4.36876923032296,-1.7811967209616646],[25.18525640768373,0],[6.423487178831019,12.269360653328114],[0,4.45796721223925],[-4.049589743176077,1.910557376673964],[-23.419794869402537,0]],"o":[[21.75407692085474,0],[5.954692307084034,0.6866065572422059],[0,4.995311474428802],[-5.615564101990471,13.443557374408988],[-24.327461535976486,0],[-3.6306666662957934,-2.049868852056441],[0,-4.766442622014734],[7.181538460804866,-14.558049177468801],[0,0]],"v":[[57.35256409670553,0],[106.12717947633858,21.971409831750588],[116.69999998807907,33.832786878601446],[109.24915383499402,44.888147532167984],[57.35256409670553,60.69999998807907],[6.074384614764115,46.21160654830151],[0,35.822950812636826],[6.852384614684643,25.026311470494896],[57.35256409670553,0]]}],"t":27},{"o":{"x":0.65,"y":0},"i":{"x":0.35,"y":0},"s":[{"c":true,"i":[[0,0],[-8.149051281218854,-13.214688521994919],[0,-5.303786884204286],[2.9923076920020275,-2.1692786880985637],[26.033076920417642,0],[7.051871794151445,11.31408196499113],[0,5.462999998927117],[-5.316333332790269,1.2239508194317583],[-22.970948715602233,0]],"o":[[22.033358972108264,0],[4.797666666176584,1.552327868547596],[0,3.9703770484005823],[-4.707897435416523,14.677459013510923],[-23.589358971949316,0],[-5.017102563590067,-1.4229672128352961],[0,-5.6719672120008315],[7.520666665898429,-14.120213111981016],[0,0]],"v":[[59.34743589137354,0],[108.44123075815348,22.47890163492961],[116.69999998807907,33.832786878601446],[111.76269229627573,43.495032778343216],[59.34743589137354,60.69999998807907],[8.69764102475256,47.30619671202097],[0,35.822950812636826],[9.276153845206286,24.190442618200034],[59.34743589137354,0]]}],"t":45},{"o":{"x":0.65,"y":0},"i":{"x":0.35,"y":0},"s":[{"c":true,"i":[[0,0],[-8.149051281218854,-13.214688521994919],[0,-5.303786884204286],[2.9923076920020275,-2.1692786880985637],[26.033076920417642,0],[7.051871794151445,11.31408196499113],[0,5.462999998927117],[-5.316333332790269,1.2239508194317583],[-22.970948715602233,0]],"o":[[22.033358972108264,0],[4.797666666176584,1.552327868547596],[0,3.9703770484005823],[-4.707897435416523,14.677459013510923],[-23.589358971949316,0],[-5.017102563590067,-1.4229672128352961],[0,-5.6719672120008315],[7.520666665898429,-14.120213111981016],[0,0]],"v":[[59.34743589137354,0],[108.44123075815348,22.47890163492961],[116.69999998807907,33.832786878601446],[111.76269229627573,43.495032778343216],[59.34743589137354,60.69999998807907],[8.69764102475256,47.30619671202097],[0,35.822950812636826],[9.276153845206286,24.190442618200034],[59.34743589137354,0]]}],"t":69},{"o":{"x":0.65,"y":0},"i":{"x":0.35,"y":0},"s":[{"c":true,"i":[[0,0],[-7.52099159588333,-14.120213111981016],[0,-5.6719672120008315],[5.0173193272272085,-1.4229672128352961],[23.590378148891343,0],[7.052176469879992,11.31408196499113],[0,5.462999998927117],[-5.316563024676147,1.2239508194317583],[-22.97194117416354,0]],"o":[[22.97194117416354,0],[5.316563024676147,1.2239508194317583],[0,5.462999998927117],[-7.052176469879992,11.31408196499113],[-23.590378148891343,0],[-5.0173193272272085,-1.4229672128352961],[0,-5.6719672120008315],[7.52099159588333,-14.120213111981016],[0,0]],"v":[[59.349999994039536,0],[109.42344536716197,24.190442618200034],[118.69999998807907,35.822950812636826],[110.00198318222992,47.30619671202097],[59.349999994039536,60.69999998807907],[8.698016805849155,47.30619671202097],[0,35.822950812636826],[9.276554620917105,24.190442618200034],[59.349999994039536,0]]}],"t":87},{"o":{"x":0.65,"y":0},"i":{"x":0.35,"y":0},"s":[{"c":true,"i":[[0,0],[-7.52099159588333,-14.120213111981016],[0,-5.6719672120008315],[5.0173193272272085,-1.4229672128352961],[23.590378148891343,0],[7.052176469879992,11.31408196499113],[0,5.462999998927117],[-5.316563024676147,1.2239508194317583],[-22.97194117416354,0]],"o":[[22.97194117416354,0],[5.316563024676147,1.2239508194317583],[0,5.462999998927117],[-7.052176469879992,11.31408196499113],[-23.590378148891343,0],[-5.0173193272272085,-1.4229672128352961],[0,-5.6719672120008315],[7.52099159588333,-14.120213111981016],[0,0]],"v":[[59.349999994039536,0],[109.42344536716197,24.190442618200034],[118.69999998807907,35.822950812636826],[110.00198318222992,47.30619671202097],[59.349999994039536,60.69999998807907],[8.698016805849155,47.30619671202097],[0,35.822950812636826],[9.276554620917105,24.190442618200034],[59.349999994039536,0]]}],"t":147},{"o":{"x":0.65,"y":0},"i":{"x":0.35,"y":0},"s":[{"c":true,"i":[[0,0],[-8.308641024792296,-12.946016390900143],[0,-6.129704916828969],[4.36876923032296,-1.7811967209616646],[25.18525640768373,0],[6.423487178831019,12.269360653328114],[0,4.45796721223925],[-4.049589743176077,1.910557376673964],[-23.419794869402537,0]],"o":[[21.75407692085474,0],[5.954692307084034,0.6866065572422059],[0,4.995311474428802],[-5.615564101990471,13.443557374408988],[-24.327461535976486,0],[-3.6306666662957934,-2.049868852056441],[0,-4.766442622014734],[7.181538460804866,-14.558049177468801],[0,0]],"v":[[57.35256409670553,0],[106.12717947633858,21.971409831750588],[116.69999998807907,33.832786878601446],[109.24915383499402,44.888147532167984],[57.35256409670553,60.69999998807907],[6.074384614764115,46.21160654830151],[0,35.822950812636826],[6.852384614684643,25.026311470494896],[57.35256409670553,0]]}],"t":165},{"s":[{"c":true,"i":[[0,0],[-8.308641024792296,-12.946016390900143],[0,-6.129704916828969],[4.36876923032296,-1.7811967209616646],[25.18525640768373,0],[6.423487178831019,12.269360653328114],[0,4.45796721223925],[-4.049589743176077,1.910557376673964],[-23.419794869402537,0]],"o":[[21.75407692085474,0],[5.954692307084034,0.6866065572422059],[0,4.995311474428802],[-5.615564101990471,13.443557374408988],[-24.327461535976486,0],[-3.6306666662957934,-2.049868852056441],[0,-4.766442622014734],[7.181538460804866,-14.558049177468801],[0,0]],"v":[[57.35256409670553,0],[106.12717947633858,21.971409831750588],[116.69999998807907,33.832786878601446],[109.24915383499402,44.888147532167984],[57.35256409670553,60.69999998807907],[6.074384614764115,46.21160654830151],[0,35.822950812636826],[6.852384614684643,25.026311470494896],[57.35256409670553,0]]}],"t":192}]}},{"ty":"st","bm":0,"hd":false,"nm":"","lc":1,"lj":1,"ml":4,"o":{"a":0,"k":100},"w":{"a":1,"k":[{"o":{"x":0.65,"y":0},"i":{"x":0.35,"y":0},"s":[1],"t":0},{"o":{"x":0.65,"y":0},"i":{"x":0.35,"y":0},"s":[1],"t":27},{"o":{"x":0.65,"y":0},"i":{"x":0.35,"y":0},"s":[1],"t":45},{"o":{"x":0.65,"y":0},"i":{"x":0.35,"y":0},"s":[1],"t":69},{"o":{"x":0.65,"y":0},"i":{"x":0.35,"y":0},"s":[1],"t":87},{"o":{"x":0.65,"y":0},"i":{"x":0.35,"y":0},"s":[1],"t":147},{"o":{"x":0.65,"y":0},"i":{"x":0.35,"y":0},"s":[1],"t":165},{"s":[1],"t":192}]},"c":{"a":0,"k":[0.251,0.3059,0.302]}},{"ty":"fl","bm":0,"hd":false,"nm":"","c":{"a":0,"k":[1,1,1]},"r":1,"o":{"a":0,"k":100}}],"ind":8}],"v":"5.7.0","fr":60,"op":165,"ip":0,"assets":[]}